LICENSE
README.md
setup.py
videojoiner.py
videojoiner.egg-info/PKG-INFO
videojoiner.egg-info/SOURCES.txt
videojoiner.egg-info/dependency_links.txt
videojoiner.egg-info/requires.txt
videojoiner.egg-info/top_level.txt