Metadata-Version: 2.1
Name: videojoiner
Version: 0.2.0
Summary: make video joining easy on windows
Home-page: https://gitlab.com/rveach/videojoiner
Author: Ryan Veach
Author-email: rveach@gmail.com
License: MIT
Keywords: Raspberry,Pi,Raspbian
Platform: UNKNOWN
Classifier: Development Status :: 4 - Beta
Classifier: License :: OSI Approved :: MIT License
Classifier: Topic :: Multimedia :: Video :: Conversion
Classifier: Operating System :: Microsoft :: Windows
Classifier: Programming Language :: Python :: 3
Requires-Python: >=3.6
License-File: LICENSE
